lumen/__init__.py
lumen/__main__.py
lumen/__version.py
lumen/_version.py
lumen/auth.py
lumen/base.py
lumen/config.py
lumen/dashboard.py
lumen/downloads.py
lumen/layout.py
lumen/panel.py
lumen/pipeline.py
lumen/rest.py
lumen/schema.py
lumen/serializers.py
lumen/state.py
lumen/util.py
lumen/validation.py
lumen/ai/__init__.py
lumen/ai/actor.py
lumen/ai/agents.py
lumen/ai/analysis.py
lumen/ai/components.py
lumen/ai/config.py
lumen/ai/controls.py
lumen/ai/coordinator.py
lumen/ai/embeddings.py
lumen/ai/embeddings_stop_words.txt
lumen/ai/export.py
lumen/ai/interceptor.py
lumen/ai/llm.py
lumen/ai/logs.py
lumen/ai/memory.py
lumen/ai/models.py
lumen/ai/schemas.py
lumen/ai/services.py
lumen/ai/tools.py
lumen/ai/translate.py
lumen/ai/ui.py
lumen/ai/utils.py
lumen/ai/vector_store.py
lumen/ai/views.py
lumen/ai/models/details.js
lumen/ai/models/split.js
lumen/ai/prompts/Actor/main.jinja2
lumen/ai/prompts/Agent/main.jinja2
lumen/ai/prompts/AnalysisAgent/main.jinja2
lumen/ai/prompts/AnalystAgent/main.jinja2
lumen/ai/prompts/BaseViewAgent/main.jinja2
lumen/ai/prompts/ChatAgent/main.jinja2
lumen/ai/prompts/Coordinator/tool_relevance.jinja2
lumen/ai/prompts/DbtslAgent/main.jinja2
lumen/ai/prompts/DbtslLookup/main.jinja2
lumen/ai/prompts/DependencyResolver/main.jinja2
lumen/ai/prompts/FunctionTool/main.jinja2
lumen/ai/prompts/IterativeTableLookup/iterative_selection.jinja2
lumen/ai/prompts/LumenBaseAgent/retry_output.jinja2
lumen/ai/prompts/Planner/follow_up.jinja2
lumen/ai/prompts/Planner/main.jinja2
lumen/ai/prompts/SQLAgent/main.jinja2
lumen/ai/prompts/TableLookup/select_columns.jinja2
lumen/ai/prompts/TableLookup/should_refresh_columns.jinja2
lumen/ai/prompts/TableLookup/should_refresh_tables.jinja2
lumen/ai/prompts/TableLookup/should_select_columns.jinja2
lumen/ai/prompts/VectorLookupTool/refine_query.jinja2
lumen/ai/prompts/VectorStore/main.jinja2
lumen/ai/prompts/VectorStore/should_situate.jinja2
lumen/ai/prompts/VegaLiteAgent/main.jinja2
lumen-0.10.1.dist-info/METADATA
lumen-0.10.1.dist-info/WHEEL
lumen-0.10.1.dist-info/entry_points.txt
lumen-0.10.1.dist-info/licenses/LICENSE
lumen-0.10.1.dist-info/RECORD
