Metadata-Version: 2.4
Name: lumen
Version: 0.10.1
Summary: A monitoring solution built on Panel.
Project-URL: Homepage, https://lumen.holoviz.org
Project-URL: Source, https://github.com/holoviz/lumen
Project-URL: HoloViz, https://holoviz.org/
Author-email: HoloViz developers <developers@holoviz.org>
Maintainer-email: HoloViz developers <developers@holoviz.org>
License: BSD
License-File: LICENSE
Classifier: Development Status :: 5 - Production/Stable
Classifier: Intended Audience :: Developers
Classifier: Intended Audience :: Science/Research
Classifier: License :: OSI Approved :: BSD License
Classifier: Natural Language :: English
Classifier: Operating System :: OS Independent
Classifier: Programming Language :: Python :: 3
Classifier: Programming Language :: Python :: 3.10
Classifier: Programming Language :: Python :: 3.11
Classifier: Programming Language :: Python :: 3.12
Classifier: Programming Language :: Python :: 3.13
Classifier: Topic :: Scientific/Engineering
Classifier: Topic :: Software Development :: Libraries
Requires-Python: >=3.10
Requires-Dist: bokeh
Requires-Dist: holoviews>=1.17.0
Requires-Dist: hvplot
Requires-Dist: intake<2
Requires-Dist: jinja2>3.0
Requires-Dist: numpy
Requires-Dist: packaging
Requires-Dist: pandas
Requires-Dist: panel>=1.6.3
Requires-Dist: param>=1.9.0
Requires-Dist: sqlglot
Provides-Extra: ai
Requires-Dist: chardet; extra == 'ai'
Requires-Dist: duckdb>=1.2.0; extra == 'ai'
Requires-Dist: griffe; extra == 'ai'
Requires-Dist: instructor>=1.6.4; extra == 'ai'
Requires-Dist: markitdown; extra == 'ai'
Requires-Dist: nbformat; extra == 'ai'
Requires-Dist: panel-graphic-walker[kernel]>=0.6.4; extra == 'ai'
Requires-Dist: pyarrow; extra == 'ai'
Requires-Dist: pydantic-extra-types; extra == 'ai'
Requires-Dist: pydantic>=2.8.0; extra == 'ai'
Requires-Dist: semchunk; extra == 'ai'
Requires-Dist: tiktoken; extra == 'ai'
Provides-Extra: ai-anthropic
Requires-Dist: anthropic; extra == 'ai-anthropic'
Requires-Dist: chardet; extra == 'ai-anthropic'
Requires-Dist: duckdb>=1.2.0; extra == 'ai-anthropic'
Requires-Dist: griffe; extra == 'ai-anthropic'
Requires-Dist: instructor>=1.6.4; extra == 'ai-anthropic'
Requires-Dist: markitdown; extra == 'ai-anthropic'
Requires-Dist: nbformat; extra == 'ai-anthropic'
Requires-Dist: panel-graphic-walker[kernel]>=0.6.4; extra == 'ai-anthropic'
Requires-Dist: pyarrow; extra == 'ai-anthropic'
Requires-Dist: pydantic-extra-types; extra == 'ai-anthropic'
Requires-Dist: pydantic>=2.8.0; extra == 'ai-anthropic'
Requires-Dist: semchunk; extra == 'ai-anthropic'
Requires-Dist: tiktoken; extra == 'ai-anthropic'
Provides-Extra: ai-llama
Requires-Dist: chardet; extra == 'ai-llama'
Requires-Dist: duckdb>=1.2.0; extra == 'ai-llama'
Requires-Dist: griffe; extra == 'ai-llama'
Requires-Dist: huggingface-hub; extra == 'ai-llama'
Requires-Dist: instructor>=1.6.4; extra == 'ai-llama'
Requires-Dist: llama-cpp-python>=0.3.0; extra == 'ai-llama'
Requires-Dist: markitdown; extra == 'ai-llama'
Requires-Dist: nbformat; extra == 'ai-llama'
Requires-Dist: panel-graphic-walker[kernel]>=0.6.4; extra == 'ai-llama'
Requires-Dist: pyarrow; extra == 'ai-llama'
Requires-Dist: pydantic-extra-types; extra == 'ai-llama'
Requires-Dist: pydantic>=2.8.0; extra == 'ai-llama'
Requires-Dist: semchunk; extra == 'ai-llama'
Requires-Dist: tiktoken; extra == 'ai-llama'
Provides-Extra: ai-local
Requires-Dist: chardet; extra == 'ai-local'
Requires-Dist: duckdb>=1.2.0; extra == 'ai-local'
Requires-Dist: griffe; extra == 'ai-local'
Requires-Dist: huggingface-hub; extra == 'ai-local'
Requires-Dist: instructor>=1.6.4; extra == 'ai-local'
Requires-Dist: markitdown; extra == 'ai-local'
Requires-Dist: nbformat; extra == 'ai-local'
Requires-Dist: panel-graphic-walker[kernel]>=0.6.4; extra == 'ai-local'
Requires-Dist: pyarrow; extra == 'ai-local'
Requires-Dist: pydantic-extra-types; extra == 'ai-local'
Requires-Dist: pydantic>=2.8.0; extra == 'ai-local'
Requires-Dist: semchunk; extra == 'ai-local'
Requires-Dist: tiktoken; extra == 'ai-local'
Provides-Extra: ai-mistralai
Requires-Dist: chardet; extra == 'ai-mistralai'
Requires-Dist: duckdb>=1.2.0; extra == 'ai-mistralai'
Requires-Dist: griffe; extra == 'ai-mistralai'
Requires-Dist: instructor>=1.6.4; extra == 'ai-mistralai'
Requires-Dist: markitdown; extra == 'ai-mistralai'
Requires-Dist: mistralai; extra == 'ai-mistralai'
Requires-Dist: nbformat; extra == 'ai-mistralai'
Requires-Dist: panel-graphic-walker[kernel]>=0.6.4; extra == 'ai-mistralai'
Requires-Dist: pyarrow; extra == 'ai-mistralai'
Requires-Dist: pydantic-extra-types; extra == 'ai-mistralai'
Requires-Dist: pydantic>=2.8.0; extra == 'ai-mistralai'
Requires-Dist: semchunk; extra == 'ai-mistralai'
Requires-Dist: tiktoken; extra == 'ai-mistralai'
Provides-Extra: ai-openai
Requires-Dist: chardet; extra == 'ai-openai'
Requires-Dist: duckdb>=1.2.0; extra == 'ai-openai'
Requires-Dist: griffe; extra == 'ai-openai'
Requires-Dist: instructor>=1.6.4; extra == 'ai-openai'
Requires-Dist: markitdown; extra == 'ai-openai'
Requires-Dist: nbformat; extra == 'ai-openai'
Requires-Dist: openai; extra == 'ai-openai'
Requires-Dist: panel-graphic-walker[kernel]>=0.6.4; extra == 'ai-openai'
Requires-Dist: pyarrow; extra == 'ai-openai'
Requires-Dist: pydantic-extra-types; extra == 'ai-openai'
Requires-Dist: pydantic>=2.8.0; extra == 'ai-openai'
Requires-Dist: semchunk; extra == 'ai-openai'
Requires-Dist: tiktoken; extra == 'ai-openai'
Provides-Extra: bigquery
Requires-Dist: google-cloud-bigquery; extra == 'bigquery'
Requires-Dist: sqlalchemy-bigquery; extra == 'bigquery'
Provides-Extra: sql
Requires-Dist: duckdb; extra == 'sql'
Requires-Dist: intake-sql; extra == 'sql'
Requires-Dist: sqlalchemy; extra == 'sql'
Provides-Extra: tests
Requires-Dist: pytest; extra == 'tests'
Requires-Dist: pytest-asyncio; extra == 'tests'
Requires-Dist: pytest-rerunfailures; extra == 'tests'
